metapulsar/__init__.py
metapulsar/file_discovery_service.py
metapulsar/layout_discovery_service.py
metapulsar/metapulsar.py
metapulsar/metapulsar_factory.py
metapulsar/mockpulsar.py
metapulsar/parameter_manager.py
metapulsar/pint_helpers.py
metapulsar/position_helpers.py
metapulsar/sandbox_tempo2.py
metapulsar/selection_utils.py
metapulsar/tim_file_analyzer.py
metapulsar-0.9.3.dist-info/licenses/LICENSE
metapulsar-0.9.3.dist-info/METADATA
metapulsar-0.9.3.dist-info/WHEEL
metapulsar-0.9.3.dist-info/top_level.txt
metapulsar-0.9.3.dist-info/RECORD
