Metadata-Version: 2.4
Name: metapulsar
Version: 0.9.3
Summary: Multi-PTA pulsar timing data combination framework for gravitational wave detection
Author-email: Rutger van Haasteren <rutger@vhaasteren.com>, Wang-Wei Yu <wangwei.yu@aei.mpg.de>, David Wright <dcw3.dev@gmail.com>
License: MIT
Project-URL: Homepage, https://github.com/vhaasteren/metapulsar
Project-URL: Repository, https://github.com/vhaasteren/metapulsar
Project-URL: Documentation, https://metapulsar.readthedocs.io
Project-URL: Issues, https://github.com/vhaasteren/metapulsar/issues
Keywords: pulsar,timing,gravitational-waves,pta,astronomy
Classifier: Development Status :: 3 - Alpha
Classifier: Intended Audience :: Science/Research
Classifier: License :: OSI Approved :: MIT License
Classifier: Operating System :: OS Independent
Classifier: Programming Language :: Python :: 3
Classifier: Programming Language :: Python :: 3.9
Classifier: Programming Language :: Python :: 3.10
Classifier: Programming Language :: Python :: 3.11
Classifier: Programming Language :: Python :: 3.12
Classifier: Topic :: Scientific/Engineering :: Astronomy
Classifier: Topic :: Scientific/Engineering :: Physics
Requires-Python: >=3.9
License-File: LICENSE
Requires-Dist: numpy>=1.20.0
Requires-Dist: astropy>=5.0.0
Requires-Dist: scipy>=1.7.0
Requires-Dist: pint-pulsar>=0.9.0
Requires-Dist: enterprise-pulsar>=3.0.0
Requires-Dist: loguru>=0.7.3
Provides-Extra: dev
Requires-Dist: pytest>=6.0; extra == "dev"
Requires-Dist: pytest-cov>=2.0; extra == "dev"
Requires-Dist: black==25.11.0; extra == "dev"
Requires-Dist: mypy>=0.900; extra == "dev"
Requires-Dist: flake8>=4.0; extra == "dev"
Provides-Extra: docs
Requires-Dist: sphinx>=4.0; extra == "docs"
Requires-Dist: sphinx-rtd-theme>=1.0; extra == "docs"
Requires-Dist: sphinx-autodoc-typehints>=1.0; extra == "docs"
Requires-Dist: myst-parser>=1.0; extra == "docs"
Requires-Dist: linkify-it-py>=2.0; extra == "docs"
Provides-Extra: libstempo
Requires-Dist: libstempo>=2.0.0; extra == "libstempo"
Dynamic: license-file
